README.md
pyproject.toml
setup.cfg
setup.py
selfCipherX/__init__.py
selfCipherX/client.py
selfCipherX.egg-info/PKG-INFO
selfCipherX.egg-info/SOURCES.txt
selfCipherX.egg-info/dependency_links.txt
selfCipherX.egg-info/requires.txt
selfCipherX.egg-info/top_level.txt
selfCipherX/crypto/__init__.py
selfCipherX/crypto/crypto.py
selfCipherX/gadgets/__init__.py
selfCipherX/gadgets/classino.py
selfCipherX/gadgets/exceptions.py
selfCipherX/gadgets/methods.py
selfCipherX/network/__init__.py
selfCipherX/network/connection.py
selfCipherX/network/proxies.py
selfCipherX/sessions/__init__.py
selfCipherX/sessions/sqliteSession.py
selfCipherX/sessions/stringSession.py
selfCipherX/structs/__init__.py
selfCipherX/structs/handlers.py
selfCipherX/structs/models.py
selfCipherX/structs/results.py
selfCipherX/structs/struct.py